MANIFEST.in
README.md
requirements.txt
setup.py
cli_builder/__init__.py
cli_builder/version.py
cli_builder.egg-info/PKG-INFO
cli_builder.egg-info/SOURCES.txt
cli_builder.egg-info/dependency_links.txt
cli_builder.egg-info/not-zip-safe
cli_builder.egg-info/top_level.txt