Metadata-Version: 2.1
Name: cli-builder
Version: 0.1.5
Summary: Decorators for building command group CLIs
Home-page: https://github.com/xbrianh/cli-builder
Author: Brian Hannafious
Author-email: bhannafi@ucsc.edu
License: MIT
Platform: MacOS X
Platform: Posix
Classifier: Intended Audience :: Developers
Classifier: License :: OSI Approved :: MIT License
Classifier: Programming Language :: Python :: 3.7
